LICENSE
MANIFEST.in
README.rst
setup.py
django_province.egg-info/PKG-INFO
django_province.egg-info/SOURCES.txt
django_province.egg-info/dependency_links.txt
django_province.egg-info/requires.txt
django_province.egg-info/top_level.txt
province/__init__.py
province/admin.py
province/apps.py
province/models.py
province/tests.py
province/views.py
province/api/__init__.py
province/api/__init__.pyc
province/api/serializers.py
province/api/serializers.pyc
province/api/urls-city.py
province/api/urls-city.pyc
province/api/urls-shahrak.py
province/api/urls-shahrak.pyc
province/api/urls-town.py
province/api/urls-town.pyc
province/api/urls.py
province/api/urls.pyc
province/api/views.py
province/api/views.pyc
province/fixtures/province.json
province/migrations/0001_initial.py
province/migrations/__init__.py