Metadata-Version: 1.1
Name: django-province
Version: 0.2
Summary: A simple Django app to show and user province, city, town and shahrak in Iran.
Home-page: https://www.aparnik.com/
Author: Ali Zahedi Gol
Author-email: zahedi@aparnik.com
License: BSD License
Platform: UNKNOWN
Classifier: Environment :: Web Environment
Classifier: Framework :: Django
Classifier: Framework :: Django :: 1.4
Classifier: Intended Audience :: Developers
Classifier: License :: OSI Approved :: BSD License
Classifier: Operating System :: OS Independent
Classifier: Programming Language :: Python
Classifier: Programming Language :: Python :: 2.7
Classifier: Topic :: Internet :: WWW/HTTP
Classifier: Topic :: Internet :: WWW/HTTP :: Dynamic Content
